{"cameraMode":{"drawMode":0,"name":"Shaded","section":"Shading Mode"},"sceneLighting":true,"audioPlay":false,"sceneViewState":{"m_AlwaysRefresh":false,"showFog":true,"showSkybox":false,"showFlares":true,"showImageEffects":true,"showParticleSystems":true,"showVisualEffectGraphs":true,"m_FxEnabled":true},"in2DMode":false,"pivot":{"x":5.119242191314697,"y":3.021296501159668,"z":-21.32148551940918},"rotation":{"x":-0.22286434471607209,"y":-0.44614821672439577,"z":0.11574974656105042,"w":-0.8591699600219727},"size":3.525714159011841,"orthographic":false}